s3_extend/__init__.py
s3_extend/s3a.py
s3_extend/s3c.py
s3_extend/s3e.py
s3_extend/s3p.py
s3_extend/s3r.py
s3_extend/s3rh.py
s3_extend/s3rp.py
s3_extend/gateways/__init__.py
s3_extend/gateways/arduino_gateway.py
s3_extend/gateways/cpx_gateway.py
s3_extend/gateways/esp8266_gateway.py
s3_extend/gateways/picoboard_gateway.py
s3_extend/gateways/robohat_gateway.py
s3_extend/gateways/rpi_gateway.py
s3_extend/gateways/rpi_pico_gateway.py
s3_extend/gateways/servo.py
s3_extend/gateways/sonar.py
s3_extend/gateways/stepper.py
s3_extend/gateways/ws_gateway.py
scratch_gpio_extend/__init__.py
scratch_gpio_extend/s3a.py
scratch_gpio_extend/s3c.py
scratch_gpio_extend/s3e.py
scratch_gpio_extend/s3p.py
scratch_gpio_extend/s3r.py
scratch_gpio_extend/s3rh.py
scratch_gpio_extend/s3rp.py
scratch_gpio_extend/gateways/__init__.py
scratch_gpio_extend/gateways/arduino_gateway.py
scratch_gpio_extend/gateways/cpx_gateway.py
scratch_gpio_extend/gateways/esp8266_gateway.py
scratch_gpio_extend/gateways/picoboard_gateway.py
scratch_gpio_extend/gateways/robohat_gateway.py
scratch_gpio_extend/gateways/rpi_gateway.py
scratch_gpio_extend/gateways/rpi_pico_gateway.py
scratch_gpio_extend/gateways/servo.py
scratch_gpio_extend/gateways/sonar.py
scratch_gpio_extend/gateways/stepper.py
scratch_gpio_extend/gateways/ws_gateway.py
scratch_gpio_extend-0.1.dist-info/LICENSE
scratch_gpio_extend-0.1.dist-info/METADATA
scratch_gpio_extend-0.1.dist-info/WHEEL
scratch_gpio_extend-0.1.dist-info/entry_points.txt
scratch_gpio_extend-0.1.dist-info/top_level.txt
scratch_gpio_extend-0.1.dist-info/RECORD
