Metadata-Version: 2.1
Name: scratch-gpio-extend
Version: 0.1
Summary: scratch3 gpio test
Home-page: https://github.com/barkhaneum/scratch_gpio_dev
Author: BarkHaneum
Author-email: majingazzz@naver.com
License: GNU Affero General Public License v3 or later (AGPLv3+)
Keywords: Scratch3,Arduino,ESP-8266,Raspberry Pi
Platform: UNKNOWN
Classifier: Development Status :: 5 - Production/Stable
Classifier: Environment :: Other Environment
Classifier: Intended Audience :: Education
Classifier: Intended Audience :: Developers
Classifier: License :: OSI Approved :: GNU Affero General Public License v3 or later (AGPLv3+)
Classifier: Operating System :: OS Independent
Classifier: Programming Language :: Python :: 3.7
Classifier: Topic :: Education
Classifier: Topic :: Software Development
Classifier: Topic :: System :: Hardware
Requires-Dist: pymata-cpx
Requires-Dist: pymata-express (>=1.11)
Requires-Dist: pymata-rh
Requires-Dist: python-banyan (>=3.9)
Requires-Dist: telemetrix-aio
Requires-Dist: tmx-pico-aio
